libmoon/__init__.py
libmoon/example.py
libmoon/problem/__init__.py
libmoon/problem/mop.py
libmoon/problem/mtl/__init__.py
libmoon/problem/mtl/fair_classify.py
libmoon/problem/mtl/mnist.py
libmoon/problem/mtl/objectives.py
libmoon/problem/mtl/loaders/__init__.py
libmoon/problem/mtl/loaders/adult_loader.py
libmoon/problem/mtl/loaders/compas_loader.py
libmoon/problem/mtl/loaders/credit_loader.py
libmoon/problem/mtl/loaders/multimnist_loader.py
libmoon/problem/mtl/model/__init__.py
libmoon/problem/mtl/model/simple.py
libmoon/problem/synthetic/__init__.py
libmoon/problem/synthetic/dtlz.py
libmoon/problem/synthetic/maf.py
libmoon/problem/synthetic/re.py
libmoon/problem/synthetic/re_original.py
libmoon/problem/synthetic/vlmop.py
libmoon/problem/synthetic/wfg.py
libmoon/problem/synthetic/zdt.py
libmoon/solver/__init__.py
libmoon/solver/gradient/__init__.py
libmoon/solver/gradient/base_solver.py
libmoon/solver/gradient/core_solver.py
libmoon/solver/gradient/epo_solver.py
libmoon/solver/gradient/functions_evaluation.py
libmoon/solver/gradient/functions_hv_grad_3d.py
libmoon/solver/gradient/functions_hv_python3.py
libmoon/solver/gradient/gradhv.py
libmoon/solver/gradient/mgda_core.py
libmoon/solver/gradient/mgda_solver.py
libmoon/solver/gradient/min_norm_solvers_numpy.py
libmoon/solver/gradient/moosvgd.py
libmoon/solver/gradient/pmgda.py
libmoon/solver/gradient/pmtl.py
libmoon/solver/gradient/run/__init__.py
libmoon/solver/gradient/run/run_grad.py
libmoon/solver/gradient/utils/__init__.py
libmoon/solver/gradient/utils/util.py
libmoon/solver/mobo/__init__.py
libmoon/solver/mobo/dirhvego.py
libmoon/solver/mobo/mobod.py
libmoon/solver/mobo/utils/__init__.py
libmoon/solver/mobo/utils/termination.py
libmoon/solver/moea/__init__.py
libmoon/solver/moea/moead.py
libmoon/solver/moea/moead_pfl.py
libmoon/solver/moea/utils/__init__.py
libmoon/solver/moea/utils/decomposition.py
libmoon/solver/moea/utils/genetic_operator.py
libmoon/solver/moea/utils/population.py
libmoon-0.1.7.dist-info/LICENSE
libmoon-0.1.7.dist-info/METADATA
libmoon-0.1.7.dist-info/WHEEL
libmoon-0.1.7.dist-info/top_level.txt
libmoon-0.1.7.dist-info/RECORD
